fomc_hf_nlp/__init__.py
fomc_hf_nlp/__version__.py
fomc_hf_nlp/ingestor/__init__.py
fomc_hf_nlp/ingestor/abstract_ingestor.py
fomc_hf_nlp/ingestor/fomc_data.py
fomc_hf_nlp/ingestor/pressconf_ingestor.py
fomc_hf_nlp/ingestor/statement_ingestor.py
fomc_hf_nlp/market/__init___.py
fomc_hf_nlp/market/market_loader.py
fomc_hf_nlp/market/market_processor.py
fomc_hf_nlp/models/__init__.py
fomc_hf_nlp/models/fomc_event.py
fomc_hf_nlp/models/fomc_meeting.py
fomc_hf_nlp/models/transcript.py
fomc_hf_nlp/quant_analysis/data_prep.py
fomc_hf_nlp/quant_analysis/plots.py
fomc_hf_nlp/quant_analysis/stats.py
fomc_hf_nlp/sentiment/__init__.py
fomc_hf_nlp/sentiment/nlp_pipeline.py
fomc_hf_nlp/sentiment/sentiment_scorer.py
fomc_hf_nlp/tools/__init__.py
fomc_hf_nlp/tools/chunker.py
fomc_hf_nlp/tools/logging_config.py
fomc_hf_nlp/tools/utilities.py
fomc_hf_nlp-0.1.1.dist-info/licenses/LICENSE
fomc_hf_nlp-0.1.1.dist-info/METADATA
fomc_hf_nlp-0.1.1.dist-info/WHEEL
fomc_hf_nlp-0.1.1.dist-info/top_level.txt
fomc_hf_nlp-0.1.1.dist-info/RECORD
