Metadata-Version: 2.4
Name: fomc-hf-nlp
Version: 0.1.1
Summary: A Statistical Study of High Frequency Crypto Reactions to FOMC NLP Tone
Author-email: Thibault Charbonnier <thibault.charbonnier@ensae.fr>
License: GNU GENERAL PUBLIC LICENSE
Project-URL: Homepage, https://github.com/thibault-charbonnier/fomc-nlp-intraday-crypto
Project-URL: Issues, https://github.com/thibault-charbonnier/fomc-nlp-intraday-crypto/issues
Keywords: FOMC,NLP,RoBERTa,event study,crypto,high-frequency,quant,statistics,econometrics
Classifier: Programming Language :: Python :: 3
Classifier: License :: OSI Approved :: GNU General Public License v3 (GPLv3)
Classifier: Operating System :: OS Independent
Classifier: Intended Audience :: Science/Research
Classifier: Topic :: Scientific/Engineering :: Information Analysis
Requires-Python: >=3.10
License-File: LICENSE
Requires-Dist: numpy>=1.26
Requires-Dist: pandas>=2.1
Requires-Dist: scipy>=1.11
Requires-Dist: statsmodels>=0.14
Requires-Dist: matplotlib>=3.8
Requires-Dist: scikit-learn>=1.3
Requires-Dist: requests>=2.31
Requires-Dist: beautifulsoup4>=4.12
Requires-Dist: pdfminer.six>=20231228
Requires-Dist: tqdm>=4.66
Requires-Dist: rich>=13.7
Requires-Dist: regex>=2023.12
Requires-Dist: transformers>=4.44
Requires-Dist: huggingface-hub>=0.23
Requires-Dist: accelerate>=0.33
Requires-Dist: torch>=2.2
Requires-Dist: tokenizers>=0.15
Requires-Dist: seaborn>=0.13
Provides-Extra: io
Requires-Dist: pyarrow>=14.0; extra == "io"
Provides-Extra: dev
Requires-Dist: pytest>=8; extra == "dev"
Requires-Dist: ruff>=0.6; extra == "dev"
Requires-Dist: black>=24.4; extra == "dev"
Requires-Dist: build; extra == "dev"
Requires-Dist: twine; extra == "dev"
Dynamic: license-file
